pyexcel_xlsx/__init__.py
pyexcel_xlsx/xlsxr.py
pyexcel_xlsx/xlsxw.py
pyexcel_xlsx-0.5.8.dist-info/LICENSE
pyexcel_xlsx-0.5.8.dist-info/METADATA
pyexcel_xlsx-0.5.8.dist-info/WHEEL
pyexcel_xlsx-0.5.8.dist-info/top_level.txt
pyexcel_xlsx-0.5.8.dist-info/RECORD
