Metadata-Version: 1.1
Name: pyexcel-xlsx
Version: 0.5.8
Summary: A wrapper library to read, manipulate and write data in xlsx and xlsmformat
Home-page: https://github.com/pyexcel/pyexcel-xlsx
Author: C.W.
Author-email: info@pyexcel.org
License: New BSD
Download-URL: https://github.com/pyexcel/pyexcel-xlsx/archive/0.5.8.tar.gz
Keywords: python,xlsx
Platform: UNKNOWN
Classifier: Topic :: Software Development :: Libraries
Classifier: Programming Language :: Python
Classifier: Intended Audience :: Developers
Classifier: Programming Language :: Python :: 2.6
Classifier: Programming Language :: Python :: 2.7
Classifier: Programming Language :: Python :: 3.3
Classifier: Programming Language :: Python :: 3.4
Classifier: Programming Language :: Python :: 3.5
Classifier: Programming Language :: Python :: 3.6
Classifier: Programming Language :: Python :: 3.7
Classifier: Programming Language :: Python :: 3.8
Classifier: Programming Language :: Python :: Implementation :: PyPy
